lxmlmiddleware
