Metadata-Version: 1.0
Name: lxmlmiddleware
Version: 0.2
Summary: stack of middleware to deal with a response as a LXML etree
Home-page: http://k0s.org/hg/lxmlmiddleware
Author: Jeff Hammel
Author-email: k0scist@gmail.com
License: UNKNOWN
Platform: UNKNOWN
